nano_keras/__init__.py
nano_keras/models.py
nano_keras/activations/Activation.py
nano_keras/activations/ELU.py
nano_keras/activations/LeakyReLU.py
nano_keras/activations/ReLU.py
nano_keras/activations/Sigmoid.py
nano_keras/activations/Softmax.py
nano_keras/activations/Tanh.py
nano_keras/activations/__init__.py
nano_keras/callbacks/CSVLogger.py
nano_keras/callbacks/EarlyStopping.py
nano_keras/callbacks/LearningRateScheduler.py
nano_keras/callbacks/__init__.py
nano_keras/callbacks/callback.py
nano_keras/initializers/ConstantInitializer.py
nano_keras/initializers/Initializers.py
nano_keras/initializers/RandomInitializers.py
nano_keras/initializers/__init__.py
nano_keras/layers/Conv.py
nano_keras/layers/Dense.py
nano_keras/layers/Dropout.py
nano_keras/layers/Embedding.py
nano_keras/layers/Flatten.py
nano_keras/layers/GRU.py
nano_keras/layers/Input.py
nano_keras/layers/LSTM.py
nano_keras/layers/Layer.py
nano_keras/layers/LayerWithParams.py
nano_keras/layers/PoolingLayers.py
nano_keras/layers/Reshape.py
nano_keras/layers/__init__.py
nano_keras/losses/BCE.py
nano_keras/losses/CCE.py
nano_keras/losses/Hinge.py
nano_keras/losses/Huber.py
nano_keras/losses/Loss.py
nano_keras/losses/MAE.py
nano_keras/losses/MSE.py
nano_keras/losses/__init__.py
nano_keras/optimizers/AdaMax.py
nano_keras/optimizers/Adadelta.py
nano_keras/optimizers/Adafactor.py
nano_keras/optimizers/Adagrad.py
nano_keras/optimizers/Adam.py
nano_keras/optimizers/AdamW.py
nano_keras/optimizers/NAdam.py
nano_keras/optimizers/Optimizer.py
nano_keras/optimizers/RMSProp.py
nano_keras/optimizers/SGD.py
nano_keras/optimizers/__init__.py
nano_keras/regulizers/L1.py
nano_keras/regulizers/L1L2.py
nano_keras/regulizers/L2.py
nano_keras/regulizers/Regularizer.py
nano_keras/regulizers/__init__.py
nano_keras-1.2.1.dist-info/LICENSE
nano_keras-1.2.1.dist-info/METADATA
nano_keras-1.2.1.dist-info/WHEEL
nano_keras-1.2.1.dist-info/top_level.txt
nano_keras-1.2.1.dist-info/RECORD
