Metadata-Version: 2.1
Name: nano-keras
Version: 1.2.1
Summary: Deep learning library made with numpy in the style of Keras API
Home-page: https://github.com/MarcelWinterot/nano-keras
Author: Marcel Winterot
Author-email: m.winterot1@gmail.com
License: MIT
Keywords: python,machine-learning,machine-learning-library,keras,numpy
Platform: UNKNOWN
Classifier: Intended Audience :: Developers
Classifier: Programming Language :: Python :: 3
Classifier: Operating System :: Unix
Classifier: Operating System :: Microsoft :: Windows
License-File: LICENSE
Requires-Dist: numpy
